ynj/__init__.py
ynj-0.1.0.dist-info/LICENSE
ynj-0.1.0.dist-info/METADATA
ynj-0.1.0.dist-info/WHEEL
ynj-0.1.0.dist-info/entry_points.txt
ynj-0.1.0.dist-info/top_level.txt
ynj-0.1.0.dist-info/RECORD
