Metadata-Version: 2.1
Name: ynj
Version: 0.1.0
Summary: Compile Jinja templates with YAML variables
Home-page: https://gitlab.com/carbolymer/ynj
Author: carbolymer
Author-email: carbolymer@gmail.com
License: UNKNOWN
Platform: UNKNOWN
Classifier: Programming Language :: Python :: 3
Classifier: License :: OSI Approved :: GNU General Public License v3 (GPLv3)
Classifier: Operating System :: OS Independent
Classifier: Topic :: System :: Systems Administration
Classifier: Topic :: System :: Software Distribution
Requires-Dist: Jinja2
Requires-Dist: pyyaml
